torrent_worker_coordinator/__init__.py
torrent_worker_coordinator/app.py
torrent_worker_coordinator/app_schemas.py
torrent_worker_coordinator/asyncwrap.py
torrent_worker_coordinator/client.py
torrent_worker_coordinator/db.py
torrent_worker_coordinator/info_hash.py
torrent_worker_coordinator/log.py
torrent_worker_coordinator/models.py
torrent_worker_coordinator/paths.py
torrent_worker_coordinator/settings.py
torrent_worker_coordinator/task_background.py
torrent_worker_coordinator/task_download_github.py
torrent_worker_coordinator/task_populate_torrents.py
torrent_worker_coordinator/torrent_manager.py
torrent_worker_coordinator/types.py
torrent_worker_coordinator/util.py
torrent_worker_coordinator/test/run_server_in_thread.py
torrent_worker_coordinator/test/test_app.py
torrent_worker_coordinator-1.0.19.dist-info/LICENSE
torrent_worker_coordinator-1.0.19.dist-info/METADATA
torrent_worker_coordinator-1.0.19.dist-info/WHEEL
torrent_worker_coordinator-1.0.19.dist-info/top_level.txt
torrent_worker_coordinator-1.0.19.dist-info/RECORD
