Metadata-Version: 2.1
Name: torrent-worker-coordinator
Version: 1.0.19
Summary: Coordinates Torrents
Home-page: https://github.com/zackees/torrent-worker-coordinator
Maintainer: Zachary Vorhies
License: BSD 3-Clause License
Keywords: Zach Vorhies
Classifier: Programming Language :: Python :: 3
Requires-Python: >=3.10
License-File: LICENSE
Requires-Dist: fastapi
Requires-Dist: uvicorn[standard]
Requires-Dist: python-multipart
Requires-Dist: multipart
Requires-Dist: pathvalidate
Requires-Dist: concurrent-log-handler
Requires-Dist: file_read_backwards
Requires-Dist: colorama
Requires-Dist: sqlalchemy
Requires-Dist: httpx
Requires-Dist: torrent-worker>=1.0.1
Requires-Dist: torf-cli
